vktoken-3.0.0.dist-info/METADATA
vktoken-3.0.0.dist-info/WHEEL
vktoken-3.0.0.dist-info/entry_points.txt
vktoken-3.0.0.dist-info/licenses/LICENSE
vktoken/__init__.py
vktoken/__main__.py
vktoken/app.py
vktoken-3.0.0.dist-info/RECORD
