Metadata-Version: 2.1
Name: vktoken
Version: 3.0.0
Summary: Tool for granting VK access token
Keywords: vk vkontakte
Author-Email: jieggii <jieggii@protonmail.com>
License: MIT
Requires-Python: >=3.8
Requires-Dist: requests>=2.31.0
